cerebrixos_tunnel/__init__.py
cerebrixos_tunnel/main.py
cerebrixos_tunnel-0.1.0.dist-info/METADATA
cerebrixos_tunnel-0.1.0.dist-info/WHEEL
cerebrixos_tunnel-0.1.0.dist-info/entry_points.txt
cerebrixos_tunnel-0.1.0.dist-info/top_level.txt
cerebrixos_tunnel-0.1.0.dist-info/RECORD
