Metadata-Version: 2.4
Name: CerebrixOS-Tunnel
Version: 0.1.0
Summary: CerebrixOS Tunnel enables secure zero-trust access to private services via OpenZiti edge tunneling.
Home-page: 
Author: ockhamlabs
Author-email: CerebrixOS <hello@ockhamlabs.ai>
License: MIT
Classifier: Programming Language :: Python :: 3
Classifier: License :: OSI Approved :: MIT License
Classifier: Operating System :: OS Independent
Requires-Python: >=3.6
Dynamic: author
Dynamic: requires-python
